ClashRoyale/__init__.py
ClashRoyale/main.py
ClashRoyale/request.py
clashroyale_api-0.0.2.dist-info/METADATA
clashroyale_api-0.0.2.dist-info/WHEEL
clashroyale_api-0.0.2.dist-info/top_level.txt
clashroyale_api-0.0.2.dist-info/RECORD
